[
  {
    "Pregunta": "¿Cómo se llama el sistema de numeración que utiliza diez símbolos (0-9)?",
    "respuesta_correcta_literal": "Sistema Decimal",
    "Nivel": "Intermedio",
    "Tema": "Sistemas de Numeración",
    "Asignatura": "Informatica_Aplicada",
    "Grado": 11,
    "TipoActividad": "opcion_multiple",
    "OpcionA": "Sistema Binario",
    "OpcionB": "Sistema Octal",
    "OpcionC": "Sistema Decimal",
    "OpcionD": "Sistema Hexadecimal",
    "Activa": true
  },
  {
    "Pregunta": "¿Cuál es la base del sistema de numeración binario?",
    "respuesta_correcta_literal": "Base 2",
    "Nivel": "Intermedio",
    "Tema": "Sistemas de Numeración",
    "Asignatura": "Informatica_Aplicada",
    "Grado": 11,
    "TipoActividad": "opcion_multiple",
    "OpcionA": "Base 8",
    "OpcionB": "Base 10",
    "OpcionC": "Base 2",
    "OpcionD": "Base 16",
    "Activa": true
  },
  {
    "Pregunta": "¿Cuál es la base del sistema de numeración hexadecimal?",
    "respuesta_correcta_literal": "Base 16",
    "Nivel": "Intermedio",
    "Tema": "Sistemas de Numeración",
    "Asignatura": "Informatica_Aplicada",
    "Grado": 11,
    "TipoActividad": "opcion_multiple",
    "OpcionA": "Base 2",
    "OpcionB": "Base 8",
    "OpcionC": "Base 10",
    "OpcionD": "Base 16",
    "Activa": true
  },
  {
    "Pregunta": "Al convertir el número decimal 10 a binario, ¿qué resultado obtienes?",
    "respuesta_correcta_literal": "1010",
    "Nivel": "Intermedio",
    "Tema": "Sistemas de Numeración",
    "Asignatura": "Informatica_Aplicada",
    "Grado": 11,
    "TipoActividad": "opcion_multiple",
    "OpcionA": "1010",
    "OpcionB": "1100",
    "OpcionC": "1001",
    "OpcionD": "1110",
    "Activa": true
  },
  {
    "Pregunta": "Al convertir el número binario 1001 a decimal, el resultado es:",
    "respuesta_correcta_literal": "9",
    "Nivel": "Intermedio",
    "Tema": "Sistemas de Numeración",
    "Asignatura": "Informatica_Aplicada",
    "Grado": 11,
    "TipoActividad": "opcion_multiple",
    "OpcionA": "8",
    "OpcionB": "9",
    "OpcionC": "10",
    "OpcionD": "11",
    "Activa": true
  },
  {
    "Pregunta": "¿Cuál es el valor decimal de la letra 'A' en hexadecimal?",
    "respuesta_correcta_literal": "10",
    "Nivel": "Intermedio",
    "Tema": "Sistemas de Numeración",
    "Asignatura": "Informatica_Aplicada",
    "Grado": 11,
    "TipoActividad": "opcion_multiple",
    "OpcionA": "9",
    "OpcionB": "10",
    "OpcionC": "11",
    "OpcionD": "12",
    "Activa": true
  },
  {
    "Pregunta": "¿Qué letra representa el valor decimal 15 en hexadecimal?",
    "respuesta_correcta_literal": "F",
    "Nivel": "Intermedio",
    "Tema": "Sistemas de Numeración",
    "Asignatura": "Informatica_Aplicada",
    "Grado": 11,
    "TipoActividad": "opcion_multiple",
    "OpcionA": "E",
    "OpcionB": "F",
    "OpcionC": "D",
    "OpcionD": "C",
    "Activa": true
  },
  {
    "Pregunta": "Un conjunto de 4 bits (la mitad de un byte) se conoce técnicamente como:",
    "respuesta_correcta_literal": "Nibble",
    "Nivel": "Intermedio",
    "Tema": "Sistemas de Numeración",
    "Asignatura": "Informatica_Aplicada",
    "Grado": 11,
    "TipoActividad": "opcion_multiple",
    "OpcionA": "Byte",
    "OpcionB": "Nibble",
    "OpcionC": "Word",
    "OpcionD": "Packet",
    "Activa": true
  },
  {
    "Pregunta": "¿Cuántos bits se necesitan para representar un dígito hexadecimal?",
    "respuesta_correcta_literal": "4",
    "Nivel": "Intermedio",
    "Tema": "Sistemas de Numeración",
    "Asignatura": "Informatica_Aplicada",
    "Grado": 11,
    "TipoActividad": "opcion_multiple",
    "OpcionA": "2",
    "OpcionB": "4",
    "OpcionC": "8",
    "OpcionD": "16",
    "Activa": true
  },
  {
    "Pregunta": "En el sistema decimal, la base es 10. ¿Cuál es la base en el sistema Octal?",
    "respuesta_correcta_literal": "8",
    "Nivel": "Intermedio",
    "Tema": "Sistemas de Numeración",
    "Asignatura": "Informatica_Aplicada",
    "Grado": 11,
    "TipoActividad": "opcion_multiple",
    "OpcionA": "2",
    "OpcionB": "8",
    "OpcionC": "16",
    "OpcionD": "64",
    "Activa": true
  }
]